CHANGES.txt
CONTRIBUTORS.txt
MANIFEST.in
README.txt
setup.cfg
setup.py
docs/HISTORY.txt
docs/INSTALL.txt
docs/LICENSE.GPL
docs/LICENSE.txt
xhostplus/__init__.py
xhostplus.textzoom.egg-info/PKG-INFO
xhostplus.textzoom.egg-info/SOURCES.txt
xhostplus.textzoom.egg-info/dependency_links.txt
xhostplus.textzoom.egg-info/entry_points.txt
xhostplus.textzoom.egg-info/namespace_packages.txt
xhostplus.textzoom.egg-info/not-zip-safe
xhostplus.textzoom.egg-info/paster_plugins.txt
xhostplus.textzoom.egg-info/requires.txt
xhostplus.textzoom.egg-info/top_level.txt
xhostplus/textzoom/README.txt
xhostplus/textzoom/__init__.py
xhostplus/textzoom/config.py
xhostplus/textzoom/configure.zcml
xhostplus/textzoom/browser/__init__.py
xhostplus/textzoom/browser/configure.zcml
xhostplus/textzoom/browser/images/fs_big.png
xhostplus/textzoom/browser/images/fs_normal.png
xhostplus/textzoom/browser/images/fs_small.png
xhostplus/textzoom/content/__init__.py
xhostplus/textzoom/content/configure.zcml
xhostplus/textzoom/interfaces/__init__.py
xhostplus/textzoom/locales/xhostplus.textzoom.pot
xhostplus/textzoom/locales/de/LC_MESSAGES/xhostplus.textzoom.mo
xhostplus/textzoom/locales/de/LC_MESSAGES/xhostplus.textzoom.po
xhostplus/textzoom/locales/en/LC_MESSAGES/xhostplus.textzoom.mo
xhostplus/textzoom/locales/en/LC_MESSAGES/xhostplus.textzoom.po
xhostplus/textzoom/portlets/__init__.py
xhostplus/textzoom/portlets/configure.zcml
xhostplus/textzoom/portlets/textzoomportlet.pt
xhostplus/textzoom/portlets/textzoomportlet.py
xhostplus/textzoom/profiles/default/browserlayer.xml
xhostplus/textzoom/profiles/default/factorytool.xml
xhostplus/textzoom/profiles/default/metadata.xml
xhostplus/textzoom/profiles/default/portlets.xml
xhostplus/textzoom/profiles/default/types.xml
xhostplus/textzoom/tests/__init__.py
xhostplus/textzoom/tests/base.py
xhostplus/textzoom/tests/base_textzoomportlet.py
xhostplus/textzoom/tests/test_doctest.py
xhostplus/textzoom/tests/test_textzoomportlet.py