Metadata-Version: 1.0
Name: xhostplus.textzoom
Version: 1.0.2
Summary: A portlet to set the base-font size.
Home-page: http://www.xhostplus.at/
Author: Andreas Stocker
Author-email: andreas.stocker@xhostplus.at
License: GPL
Platform: UNKNOWN
Classifier: Framework :: Plone
Classifier: Intended Audience :: Developers
Classifier: License :: OSI Approved :: GNU General Public License (GPL)
